xontrib/bash_completions_dirs.py
xontrib_bash_completions_dirs-0.1.6.dist-info/METADATA
xontrib_bash_completions_dirs-0.1.6.dist-info/WHEEL
xontrib_bash_completions_dirs-0.1.6.dist-info/licenses/LICENSE
xontrib_bash_completions_dirs-0.1.6.dist-info/RECORD
