Metadata-Version: 2.1
Name: xontrib-bash-completions-dirs
Version: 0.1.6
Summary: Xontrib Bash Completions Dirs
Project-URL: Code, https://codeberg.org/taconi/xontrib-bash-completions-dirs
Project-URL: Issue tracker, https://codeberg.org/taconi/xontrib-bash-completions-dirs/issues
Author-email: taconi <igor.taconi@protonmail.com>
License-Expression: GPL-3.0-or-later
License-File: LICENSE
Classifier: License :: OSI Approved :: GNU General Public License v3 or later (GPLv3+)
Classifier: Operating System :: OS Independent
Classifier: Programming Language :: Python :: 3.8
Classifier: Programming Language :: Python :: 3.9
Classifier: Programming Language :: Python :: 3.10
Classifier: Programming Language :: Python :: 3.11
Classifier: Programming Language :: Python :: 3.12
Classifier: Topic :: System :: Shells
Classifier: Topic :: System :: System Shells
Classifier: Topic :: Terminals
Requires-Python: >=3.8
Requires-Dist: xonsh>=0.13.1
